{
  "persons": [

  ],
  "organizations": [

  ],
  "areas": [
    {
      "id": "Q155",
      "identifiers": [
        {
          "scheme": "MS_FB",
          "identifier": "country:br"
        },
        {
          "scheme": "wikidata",
          "identifier": "Q155"
        }
      ],
      "associated_wikidata_positions": [
        "Q5176750"
      ],
      "type": {
        "lang:pt-br": "país",
        "lang:pt": "país",
        "lang:en": "country"
      },
      "name": {
        "lang:pt": "República Federativa do Brasil",
        "lang:en": "Federative Republic of Brazil"
      },
      "parent_id": null
    },
    {
      "id": "Q40942",
      "identifiers": [
        {
          "scheme": "MS_FB",
          "identifier": "country:br/fed:pe"
        },
        {
          "scheme": "wikidata",
          "identifier": "Q40942"
        }
      ],
      "associated_wikidata_positions": [
        "Q53739344",
        "Q53864929"
      ],
      "type": {
        "lang:pt-br": "unidades federativas",
        "lang:pt": "unidade federativa do Brasil",
        "lang:en": "Federative unit of Brazil"
      },
      "name": {
        "lang:pt": "Pernambuco"
      },
      "parent_id": "Q155"
    }
  ],
  "memberships": [

  ]
}
